SecretsServiceManager/__init__.py
SecretsServiceManager/handler.py
secretsservicemanager-0.1.1.dist-info/licenses/LICENSE
secretsservicemanager-0.1.1.dist-info/METADATA
secretsservicemanager-0.1.1.dist-info/WHEEL
secretsservicemanager-0.1.1.dist-info/top_level.txt
secretsservicemanager-0.1.1.dist-info/RECORD
