Metadata-Version: 2.4
Name: SecretsServiceManager
Version: 0.1.1
Summary: A Python package providing helper function to dynamically retrieve secrets & their values from cloud platforms like Azure or AWS.
Home-page: https://github.com/antick-coder/SecretManager-Pkg.git
Author: Antick Mazumder
Author-email: antick.majumder@gmail.com
Classifier: Programming Language :: Python :: 3
Classifier: License :: OSI Approved :: MIT License
Classifier: Operating System :: OS Independent
Requires-Python: >=3.9
License-File: LICENSE
Dynamic: author
Dynamic: author-email
Dynamic: classifier
Dynamic: description
Dynamic: description-content-type
Dynamic: home-page
Dynamic: license-file
Dynamic: requires-python
Dynamic: summary
